pgfusion/__init__.py
pgfusion/core.py
pgfusion/utils.py
pgfusion-0.0.11.dist-info/METADATA
pgfusion-0.0.11.dist-info/WHEEL
pgfusion-0.0.11.dist-info/licenses/LICENSE
pgfusion-0.0.11.dist-info/RECORD
