Metadata-Version: 2.1
Name: pgfusion
Version: 0.0.11
Summary: An asyncpg wrapper with a simple api
Project-URL: Homepage, https://github.com/waydegg/pgfusion
Project-URL: Source, https://github.com/waydegg/pgfusion
Author-email: Wayde Gilliam <waydegilliam@gmail.com>
License: MIT
License-File: LICENSE
Keywords: asyncio,asyncpg,postgres,python
Classifier: Development Status :: 3 - Alpha
Classifier: Environment :: Console
Classifier: Framework :: AsyncIO
Classifier: Intended Audience :: Developers
Classifier: License :: OSI Approved :: MIT License
Classifier: Operating System :: MacOS
Classifier: Operating System :: POSIX :: Linux
Classifier: Programming Language :: Python :: 3 :: Only
Classifier: Programming Language :: Python :: 3.10
Classifier: Programming Language :: Python :: 3.11
Classifier: Topic :: Database :: Front-Ends
Classifier: Topic :: Software Development :: Libraries :: Python Modules
Requires-Python: >=3.10.4
Requires-Dist: asyncpg==0.27.0
